digibyte_scrypt.cpython-310-darwin.so
digibyte_scrypt-1.1.0.dist-info/METADATA
digibyte_scrypt-1.1.0.dist-info/WHEEL
digibyte_scrypt-1.1.0.dist-info/top_level.txt
digibyte_scrypt-1.1.0.dist-info/RECORD
