Metadata-Version: 2.1
Name: digibyte-scrypt
Version: 1.1.0
Summary: Bindings for scrypt proof of work used by DigiByte
Home-page: https://pypi.org/project/digibyte_scrypt
Maintainer: YoshiJaeger
Maintainer-email: pypi@jaeger.berlin
License: GPLv3
Classifier: Intended Audience :: Developers
Classifier: Programming Language :: Python :: 3
Classifier: Programming Language :: Python :: 3.3
Classifier: Programming Language :: Python :: 3.4
Classifier: Programming Language :: Python :: 3.5
Classifier: Programming Language :: Python :: 3.6
Classifier: Programming Language :: Python :: 3.7
Classifier: Programming Language :: Python :: 3.8
Classifier: Programming Language :: Python :: 3.5
Classifier: Programming Language :: Python :: 3.10
